autopolicy/__init__.py
autopolicy/autopolicy.py
autopolicy/policy.py
autopolicy-0.12.0.dist-info/METADATA
autopolicy-0.12.0.dist-info/WHEEL
autopolicy-0.12.0.dist-info/RECORD
