Metadata-Version: 2.4
Name: autopolicy
Version: 0.12.0
Summary: 
Author: uname-n
Author-email: git@defend.sh
Requires-Python: >=3.12,<3.13
Classifier: Programming Language :: Python :: 3
Classifier: Programming Language :: Python :: 3.12
Requires-Dist: autogluon (>=1.5.0,<2.0.0)
Requires-Dist: joblib (>=1.5.3,<2.0.0)
Requires-Dist: pandas (>=2.3.3,<3.0.0)
Requires-Dist: polars (>=1.36.1,<2.0.0)
